fast_tort_cli/__init__.py
fast_tort_cli/__main__.py
fast_tort_cli/cli.py
fast_tort_cli/py.typed
fast_tort_cli-0.6.0.dist-info/LICENSE
fast_tort_cli-0.6.0.dist-info/METADATA
fast_tort_cli-0.6.0.dist-info/WHEEL
fast_tort_cli-0.6.0.dist-info/entry_points.txt
fast_tort_cli-0.6.0.dist-info/RECORD
