Metadata-Version: 2.1
Name: fast-tort-cli
Version: 0.6.0
Summary: 
Author: Waket Zheng
Author-email: waketzheng@gmail.com
Requires-Python: >=3.11,<4.0
Classifier: Programming Language :: Python :: 3
Classifier: Programming Language :: Python :: 3.11
Classifier: Programming Language :: Python :: 3.12
Provides-Extra: all
Requires-Dist: anyio (>=3.7.1)
Requires-Dist: black (>=23.9.1) ; extra == "all"
Requires-Dist: bumpversion (>=0.6.0,<0.7.0) ; extra == "all"
Requires-Dist: click (>=7.1.1)
Requires-Dist: coverage (>=6.5.0) ; extra == "all"
Requires-Dist: isort (>=5.12.0) ; extra == "all"
Requires-Dist: mypy (>=1.5.0) ; extra == "all"
Requires-Dist: pytest (>=8.0.2,<9.0.0) ; extra == "all"
Requires-Dist: ruff (>=0.3) ; extra == "all"
Requires-Dist: typer[all] (>=0.9.0) ; extra == "all"
